acetn/__init__.py
acetn/evolution/__init__.py
acetn/evolution/als_solver.py
acetn/evolution/evolve.py
acetn/evolution/fast_full_update.py
acetn/evolution/full_update.py
acetn/evolution/gate.py
acetn/evolution/tensor_update.py
acetn/ipeps/__init__.py
acetn/ipeps/ipeps.py
acetn/ipeps/ipeps_config.py
acetn/ipeps/site_tensor.py
acetn/ipeps/tensor_network.py
acetn/linalg/__init__.py
acetn/linalg/fused_3matmul_svd_lowrank.py
acetn/linalg/fused_matmul_svd_lowrank.py
acetn/linalg/svd_lowrank.py
acetn/measurement/__init__.py
acetn/measurement/measure.py
acetn/measurement/rdm.py
acetn/model/__init__.py
acetn/model/model.py
acetn/model/model_factory.py
acetn/model/pauli_matrix.py
acetn/model/models/__init__.py
acetn/model/models/heisenberg.py
acetn/model/models/ising.py
acetn/renormalization/__init__.py
acetn/renormalization/ctmrg.py
acetn/renormalization/directional_mover.py
acetn/renormalization/projectors.py
acetn/utils/__init__.py
acetn/utils/benchmarking.py
acetn/utils/distributed.py
acetn/utils/logger.py
acetn-0.1.3.dist-info/licenses/LICENSE
benchmarking/benchmarking_ctmrg_projectors.py
benchmarking/benchmarking_full_update.py
benchmarking/print_device_info.py
docs/conf.py
samples/01_tf_ising.py
samples/02_heisenberg.py
samples/03_custom_model.py
samples/04_compass_model.py
samples/05_honeycomb_ising.py
samples/06_kagome_ising.py
tests/integration/test_ctmrg.py
tests/integration/test_directional_mover.py
tests/integration/test_full_update.py
tests/integration/test_ground_states.py
tests/integration/test_projectors.py
tests/integration/ipeps_gs/generate_gs_ipeps.py
tests/unit/test_als.py
tests/unit/test_linalg.py
tests/unit/test_pauli_matrices.py
tests/unit/test_rdm.py
tests/unit/test_site_tensor.py
tests/unit/test_tensor_network.py
acetn-0.1.3.dist-info/METADATA
acetn-0.1.3.dist-info/WHEEL
acetn-0.1.3.dist-info/top_level.txt
acetn-0.1.3.dist-info/RECORD
