Metadata-Version: 2.4
Name: acetn
Version: 0.1.3
Summary: GPU-accelerated corner-transfer-matrix renormalization of infinite projected entangled-pair states.
Author-email: Addison Richards <adsrichards0@gmail.com>
License: Apache-2.0
Requires-Python: >=3.10
License-File: LICENSE
Requires-Dist: torch
Requires-Dist: tqdm
Requires-Dist: toml
Requires-Dist: scipy
Requires-Dist: pytest
Dynamic: license-file
